pastee.py
setup.py
pastee_client.egg-info/PKG-INFO
pastee_client.egg-info/SOURCES.txt
pastee_client.egg-info/dependency_links.txt
pastee_client.egg-info/entry_points.txt
pastee_client.egg-info/requires.txt
pastee_client.egg-info/top_level.txt