Metadata-Version: 1.1
Name: pastee-client
Version: 0.0.13
Summary: A client for Pastee, the secure pastebin.
Home-page: UNKNOWN
Author: Josh Kearney
Author-email: josh@jk0.org
License: Apache License, Version 2.0
Platform: UNKNOWN
Classifier: Development Status :: 5 - Production/Stable
Classifier: Intended Audience :: Developers
Classifier: Intended Audience :: Information Technology
Classifier: License :: OSI Approved :: Apache Software License
Classifier: Operating System :: OS Independent
Classifier: Programming Language :: Python
